pymiddy/__init__.py
pymiddy/middy.py
pymiddy/middlewares/__init__.py
pymiddy/middlewares/cors.py
pymiddy-0.1.0.dist-info/LICENSE
pymiddy-0.1.0.dist-info/METADATA
pymiddy-0.1.0.dist-info/WHEEL
pymiddy-0.1.0.dist-info/top_level.txt
pymiddy-0.1.0.dist-info/RECORD
