Metadata-Version: 2.1
Name: pymiddy
Version: 0.1.0
Summary: Middleware engine for AWS Lambda - Inspired by middyjs
Home-page: https://github.com/godvsdeity/pymiddy
Author: Alex Pasare
Author-email: alexandru.pasare@simplecoding.email
License: MIT
Platform: UNKNOWN
Classifier: Programming Language :: Python :: 3
Classifier: License :: OSI Approved :: MIT License
Classifier: Operating System :: OS Independent
